unity_yaml_normalize-0.1.5.dist-info/licenses/LICENSE
unityyamlnormalize/__init__.py
unityyamlnormalize/__main__.py
unity_yaml_normalize-0.1.5.dist-info/METADATA
unity_yaml_normalize-0.1.5.dist-info/WHEEL
unity_yaml_normalize-0.1.5.dist-info/entry_points.txt
unity_yaml_normalize-0.1.5.dist-info/top_level.txt
unity_yaml_normalize-0.1.5.dist-info/RECORD
