Metadata-Version: 2.4
Name: unity-yaml-normalize
Version: 0.1.5
Summary: Unity yaml file normalize.
Home-page: https://github.com/srz-zumix/unity-yaml-normalize/
Author: srz_zumix
Author-email: zumix.cpp@gmail.com
License: MIT
Keywords: Unity
Platform: any
Classifier: Development Status :: 4 - Beta
Classifier: Topic :: Utilities
Classifier: Programming Language :: Python
Requires-Python: >3.4
License-File: LICENSE
Requires-Dist: unityparser
Provides-Extra: test
Requires-Dist: importlib-metadata<9,>=0.12; extra == "test"
Requires-Dist: tox; extra == "test"
Requires-Dist: tox-pyenv; extra == "test"
Requires-Dist: pytest; extra == "test"
Dynamic: author
Dynamic: author-email
Dynamic: classifier
Dynamic: description
Dynamic: description-content-type
Dynamic: home-page
Dynamic: keywords
Dynamic: license
Dynamic: license-file
Dynamic: platform
Dynamic: provides-extra
Dynamic: requires-dist
Dynamic: requires-python
Dynamic: summary
